{
	"libraries":
	{
		"pxlcore":
		{
			"css": "libs/bower/pxlcore/dist/pxlcore.css",
			"js": "libs/bower/pxlcore/dist/pxlcore.js"
	    },
	    "semantic-ui":
	    {
	        "css": "libs/bower/semantic-ui/dist/semantic.min.css",
	        "js": "libs/bower/semantic-ui/dist/semantic.min.js"
	    },
	    "livestampjs":
		{
			"js":
			[
				"libs/bower/moment/moment.js",
				"libs/bower/livestampjs/livestamp.min.js"
			]
		},
		"sweetalert":
		{
			"css": "libs/bower/sweetalert/dist/sweetalert.css",
			"js": "libs/bower/sweetalert/dist/sweetalert.min.js"
		},
		"notiny":
		{
			"css": "libs/bower/notiny/dist/notiny.min.css",
			"js": "libs/bower/notiny/dist/notiny.min.js"
		}
	},
	"pages":
	{
		"all":
		{
			"libraries":
			[
				"notiny",
				"sweetalert",
				"semantic-ui",
				"pxlcore"
			]
		},
		"front":
		{
			"libraries":
			[
			]
		},
		"dashboard":
		{
			"libraries":
			[
				"livestampjs"
			]
		}
	}
}